easytrainer/__init__.py
easytrainer/config/enums.py
easytrainer/data/base_preparator.py
easytrainer/data/text.py
easytrainer/data/utils.py
easytrainer/models/base_model.py
easytrainer/models/classifier.py
easytrainer/resources/__init__.py
easytrainer/resources/stopwords-fr.txt
easytrainer-0.1.4.dist-info/LICENSE.txt
easytrainer-0.1.4.dist-info/METADATA
easytrainer-0.1.4.dist-info/WHEEL
easytrainer-0.1.4.dist-info/RECORD
